{"cameraMode":{"drawMode":0,"name":"Shaded","section":"Shading Mode"},"sceneLighting":false,"audioPlay":false,"sceneViewState":{"showFog":true,"showMaterialUpdate":false,"showSkybox":false,"showFlares":true,"showImageEffects":true,"showParticleSystems":true},"in2DMode":false,"pivot":{"x":4.890925407409668,"y":2.5800869464874269,"z":-29.78017807006836},"rotation":{"x":-0.0012279317015781999,"y":0.5938348770141602,"z":-0.001375064835883677,"w":-0.804993212223053},"size":0.9977465271949768,"orthographic":false}